akshare_mcp/__init__.py
akshare_mcp/server.py
akshare_tools-0.1.7.dist-info/METADATA
akshare_tools-0.1.7.dist-info/WHEEL
akshare_tools-0.1.7.dist-info/entry_points.txt
akshare_tools-0.1.7.dist-info/licenses/LICENSE
akshare_tools-0.1.7.dist-info/RECORD
