Metadata-Version: 2.4
Name: akshare-tools
Version: 0.1.7
Summary: Akshare MCP Server - A Model Context Protocol server for accessing Chinese stock market data via AKShare
Project-URL: Homepage, https://github.com/iefnaf/akshare-mcp
Project-URL: Repository, https://github.com/iefnaf/akshare-mcp.git
Project-URL: Documentation, https://github.com/iefnaf/akshare-mcp#readme
Project-URL: Bug Tracker, https://github.com/iefnaf/akshare-mcp/issues
Author-email: Fanfei Gao <gfanfei@gmail.com>
License: MIT
License-File: LICENSE
Keywords: akshare,chinese-market,finance,mcp,stock
Classifier: Development Status :: 4 - Beta
Classifier: Intended Audience :: Developers
Classifier: Intended Audience :: Financial and Insurance Industry
Classifier: License :: OSI Approved :: MIT License
Classifier: Operating System :: OS Independent
Classifier: Programming Language :: Python :: 3.10
Classifier: Programming Language :: Python :: 3.11
Classifier: Programming Language :: Python :: 3.12
Classifier: Topic :: Office/Business :: Financial
Classifier: Topic :: Software Development :: Libraries :: Python Modules
Requires-Python: >=3.10
Requires-Dist: akshare>=1.14.0
Requires-Dist: fastmcp>=0.1.0
Requires-Dist: pandas>=1.5.0
Provides-Extra: dev
Requires-Dist: black>=23.0.0; extra == 'dev'
Requires-Dist: mypy>=1.0.0; extra == 'dev'
Requires-Dist: pytest-asyncio>=0.21.0; extra == 'dev'
Requires-Dist: pytest>=7.0.0; extra == 'dev'
Requires-Dist: ruff>=0.1.0; extra == 'dev'
